{
  "quotes": [
    {
      "text": "The only way to do great work is to love what you do.",
      "author": "Steve Jobs",
      "category": "passion"
    },
    {
      "text": "Code is like humor. When you have to explain it, it's bad.",
      "author": "Cory House",
      "category": "coding"
    },
    {
      "text": "First, solve the problem. Then, write the code.",
      "author": "John Johnson",
      "category": "problem-solving"
    },
    {
      "text": "The best error message is the one that never shows up.",
      "author": "Thomas Fuchs",
      "category": "quality"
    },
    {
      "text": "It's not a bug – it's an undocumented feature.",
      "author": "Anonymous",
      "category": "humor"
    },
    {
      "text": "Simplicity is the soul of efficiency.",
      "author": "Austin Freeman",
      "category": "simplicity"
    },
    {
      "text": "Make it work, make it right, make it fast.",
      "author": "Kent Beck",
      "category": "process"
    },
    {
      "text": "The function of good software is to make the complex appear simple.",
      "author": "Grady Booch",
      "category": "design"
    },
    {
      "text": "Every great developer you know got there by solving problems they were unqualified to solve.",
      "author": "Patrick McKenzie",
      "category": "growth"
    },
    {
      "text": "Programming isn't about what you know; it's about what you can figure out.",
      "author": "Chris Pine",
      "category": "learning"
    },
    {
      "text": "Talk is cheap. Show me the code.",
      "author": "Linus Torvalds",
      "category": "action"
    },
    {
      "text": "Any fool can write code that a computer can understand. Good programmers write code that humans can understand.",
      "author": "Martin Fowler",
      "category": "craftsmanship"
    },
    {
      "text": "The most disastrous thing you can ever learn is your first programming language.",
      "author": "Alan Kay",
      "category": "learning"
    },
    {
      "text": "Debugging is twice as hard as writing the code in the first place.",
      "author": "Brian Kernighan",
      "category": "debugging"
    },
    {
      "text": "The best time to plant a tree was 20 years ago. The second best time is now.",
      "author": "Chinese Proverb",
      "category": "motivation"
    },
    {
      "text": "Perfection is achieved not when there is nothing more to add, but when there is nothing left to take away.",
      "author": "Antoine de Saint-Exupéry",
      "category": "simplicity"
    },
    {
      "text": "The computer was born to solve problems that did not exist before.",
      "author": "Bill Gates",
      "category": "innovation"
    },
    {
      "text": "In theory, there is no difference between theory and practice. In practice, there is.",
      "author": "Yogi Berra",
      "category": "wisdom"
    },
    {
      "text": "Before software can be reusable it first has to be usable.",
      "author": "Ralph Johnson",
      "category": "design"
    },
    {
      "text": "The only way to learn a new programming language is by writing programs in it.",
      "author": "Dennis Ritchie",
      "category": "learning"
    },
    {
      "text": "Measuring programming progress by lines of code is like measuring aircraft building progress by weight.",
      "author": "Bill Gates",
      "category": "metrics"
    },
    {
      "text": "Sometimes it pays to stay in bed on Monday, rather than spending the rest of the week debugging Monday's code.",
      "author": "Dan Salomon",
      "category": "humor"
    },
    {
      "text": "A good programmer is someone who always looks both ways before crossing a one-way street.",
      "author": "Doug Linder",
      "category": "caution"
    },
    {
      "text": "Experience is the name everyone gives to their mistakes.",
      "author": "Oscar Wilde",
      "category": "growth"
    },
    {
      "text": "The best thing about a boolean is even if you are wrong, you are only off by a bit.",
      "author": "Anonymous",
      "category": "humor"
    },
    {
      "text": "Without requirements or design, programming is the art of adding bugs to an empty text file.",
      "author": "Louis Srygley",
      "category": "process"
    },
    {
      "text": "One man's crappy software is another man's full-time job.",
      "author": "Jessica Gaston",
      "category": "humor"
    },
    {
      "text": "Deleted code is debugged code.",
      "author": "Jeff Sickel",
      "category": "simplicity"
    },
    {
      "text": "If debugging is the process of removing bugs, then programming must be the process of putting them in.",
      "author": "Edsger Dijkstra",
      "category": "debugging"
    },
    {
      "text": "Your interview is not a test of your knowledge. It's a test of your ability to communicate your knowledge.",
      "author": "Gayle McDowell",
      "category": "interview"
    }
  ],
  "todayIndex": 2,
  "lastUpdated": "2025-12-20"
}